optionmc/__init__.py
optionmc/cli.py
optionmc/models.py
optionmc/utils.py
optionmc/visualization.py
optionmc-0.1.3.4.dist-info/licenses/LICENSE
tests/__init__.py
tests/test_integration.py
tests/test_models.py
tests/test_utils.py
tests/test_visualization.py
optionmc-0.1.3.4.dist-info/METADATA
optionmc-0.1.3.4.dist-info/WHEEL
optionmc-0.1.3.4.dist-info/entry_points.txt
optionmc-0.1.3.4.dist-info/top_level.txt
optionmc-0.1.3.4.dist-info/RECORD
