Metadata-Version: 2.4
Name: optionmc
Version: 0.1.3.4
Summary: Monte Carlo simulation for European option pricing with visualization capabilities
Home-page: https://github.com/sandyherho/optionmc
Author: Sandy Herho
Author-email: sandy.herho@email.ucr.edu
License: MIT
Project-URL: Documentation, https://github.com/sandyherho/optionmc
Project-URL: Bug Reports, https://github.com/sandyherho/optionmc/issues
Project-URL: Source Code, https://github.com/sandyherho/optionmc
Keywords: finance,options,monte carlo,black-scholes,simulation,derivatives,pricing
Classifier: Development Status :: 4 - Beta
Classifier: Intended Audience :: Education
Classifier: Intended Audience :: Science/Research
Classifier: Intended Audience :: Financial and Insurance Industry
Classifier: License :: OSI Approved :: MIT License
Classifier: Programming Language :: Python :: 3
Classifier: Programming Language :: Python :: 3.7
Classifier: Programming Language :: Python :: 3.8
Classifier: Programming Language :: Python :: 3.9
Classifier: Programming Language :: Python :: 3.10
Classifier: Topic :: Scientific/Engineering :: Mathematics
Classifier: Topic :: Office/Business :: Financial
Classifier: Topic :: Office/Business :: Financial :: Investment
Classifier: Topic :: Software Development :: Libraries :: Python Modules
Requires-Python: >=3.7
License-File: LICENSE
Requires-Dist: numpy>=1.20.0
Requires-Dist: scipy>=1.7.0
Requires-Dist: matplotlib>=3.4.0
Requires-Dist: seaborn>=0.11.0
Requires-Dist: pandas>=1.3.0
Dynamic: author
Dynamic: author-email
Dynamic: classifier
Dynamic: description
Dynamic: description-content-type
Dynamic: home-page
Dynamic: keywords
Dynamic: license
Dynamic: license-file
Dynamic: project-url
Dynamic: requires-dist
Dynamic: requires-python
Dynamic: summary
